[
  {
    "target": "Se_HunterBuff",
    "overrides": {
      "populationMultiplier": "1",
      "movementSpeedPercentage": "10",
      "attackSpeedPercentage": "15",
      "abilityHaste": "40",
      "shadowWalkFarChance": "0.9",
      "shadowWalkCloseChance": "0.6",
      "shadowWalkDistanceThresholdNoAttack": "2",
      "shadowWalkDistanceThresholdOffset": "1",
      "isCleansable": "False",
      "isBeneficialBuff": "True",
      "isKilledByCrowdControlImmunity": "False",
      "scaleDurationByTenacity": "False",
      "iconOrder": "0",
      "hideOnWorldHealthBar": "False",
      "shadowWalkInterval.x": "1",
      "shadowWalkInterval.y": "2"
    }
  }
]