[
  {
    "target": "Se_Star_Nachia_L_WaltzArmor",
    "overrides": {
      "sizeAmp": "0.25",
      "requiredLevel": "20",
      "maxStarLevel": "4",
      "isCleansable": "False",
      "isBeneficialBuff": "False",
      "isKilledByCrowdControlImmunity": "False",
      "scaleDurationByTenacity": "False",
      "iconOrder": "0",
      "hideOnWorldHealthBar": "False",
      "cooldownPenalty.v0": "2.2",
      "cooldownPenalty.v1": "1.8",
      "cooldownPenalty.v2": "1.4",
      "cooldownPenalty.v3": "1",
      "cooldownPenalty.v4": "0",
      "cooldownPenalty.v5": "0",
      "cooldownPenalty.v6": "0",
      "cooldownPenalty.v7": "0",
      "cooldownPenalty.isInteger": "False",
      "cooldownPenalty.isClamped": "False",
      "cooldownPenalty.clampMin": "0",
      "cooldownPenalty.clampMax": "0",
      "cooldownPenalty.levels": "4",
      "cooldownPenalty.isParentStarEffect": "True",
      "armorAmount.v0": "50",
      "armorAmount.v1": "50",
      "armorAmount.v2": "50",
      "armorAmount.v3": "50",
      "armorAmount.v4": "0",
      "armorAmount.v5": "0",
      "armorAmount.v6": "0",
      "armorAmount.v7": "0",
      "armorAmount.isInteger": "True",
      "armorAmount.isClamped": "False",
      "armorAmount.clampMin": "0",
      "armorAmount.clampMax": "0",
      "armorAmount.levels": "4",
      "armorAmount.isParentStarEffect": "True",
      "price.0": "50",
      "price.1": "40",
      "price.2": "40",
      "price.3": "50"
    }
  }
]