[
  {
    "target": "Ai_U_BeamOfBalance_Beam",
    "overrides": {
      "checkInterval": "0.05",
      "hitInterval": "0.25",
      "maxSpeed": "10",
      "enemyDamagePerSecond.leveling": "1",
      "enemyDamagePerSecond.scalingMultiplier": "1",
      "enemyDamagePerSecond.baseValue": "0",
      "enemyDamagePerSecond.adFactor": "0",
      "enemyDamagePerSecond.apFactor": "3.5",
      "enemyDamagePerSecond.lvlFactor": "0",
      "enemyDamagePerSecond.armorFactor": "0",
      "enemyDamagePerSecond.addedHpFactor": "0",
      "enemyDamagePerSecond.critPercentageFactor": "0",
      "enemyDamagePerSecond.valueString": "3.5ap",
      "allyHealPerSecond.leveling": "1",
      "allyHealPerSecond.scalingMultiplier": "0.75",
      "allyHealPerSecond.baseValue": "0",
      "allyHealPerSecond.adFactor": "0",
      "allyHealPerSecond.apFactor": "1.5",
      "allyHealPerSecond.lvlFactor": "0",
      "allyHealPerSecond.armorFactor": "0",
      "allyHealPerSecond.addedHpFactor": "0",
      "allyHealPerSecond.critPercentageFactor": "0",
      "allyHealPerSecond.valueString": "1.5ap"
    }
  }
]